suffix_tree/__init__.py
suffix_tree/_version.py
suffix_tree/builder.py
suffix_tree/builder_factory.py
suffix_tree/lca_mixin.py
suffix_tree/mccreight.py
suffix_tree/naive.py
suffix_tree/node.py
suffix_tree/tree.py
suffix_tree/ukkonen.py
suffix_tree/util.py
suffix_tree-0.1.2.dist-info/METADATA
suffix_tree-0.1.2.dist-info/WHEEL
suffix_tree-0.1.2.dist-info/licenses/LICENSE
suffix_tree-0.1.2.dist-info/RECORD
