Metadata-Version: 2.1
Name: suffix-tree
Version: 0.1.2
Summary: A Generalized Suffix Tree for any iterable, with Lowest Common Ancestor retrieval
Project-URL: Homepage, https://github.com/cceh/suffix-tree
Project-URL: Bug Tracker, https://github.com/cceh/suffix-tree/issues
Author-email: Marcello Perathoner <marcello@perathoner.de>
License-File: LICENSE
Keywords: gusfield,lca,suffix,suffixtree,tree,ukkonen
Classifier: Intended Audience :: Developers
Classifier: Intended Audience :: Information Technology
Classifier: Intended Audience :: Science/Research
Classifier: License :: OSI Approved :: GNU General Public License v3 (GPLv3)
Classifier: Operating System :: OS Independent
Classifier: Programming Language :: Python :: 3.9
Classifier: Programming Language :: Python :: 3.10
Classifier: Programming Language :: Python :: 3.11
Classifier: Programming Language :: Python :: 3.12
Classifier: Topic :: Scientific/Engineering :: Bio-Informatics
Classifier: Topic :: Text Processing :: Indexing
Classifier: Topic :: Text Processing :: Linguistic
Requires-Python: >=3.9
